[
    {
        "Id": "1",
        "Title": "Fange i ukrainsk uniform halshugges p\u00e5 video \u2013 verden skal se den, siger Zelenskyj",
        "Data": [
            {
                "Date": "06",
                "Visits": "0"
            },
            {
                "Date": "07",
                "Visits": "0"
            },
            {
                "Date": "08",
                "Visits": "0"
            },
            {
                "Date": "09",
                "Visits": "0"
            },
            {
                "Date": "10",
                "Visits": "0"
            },
            {
                "Date": "11",
                "Visits": "0"
            },
            {
                "Date": "12",
                "Visits": "1168"
            },
            {
                "Date": "13",
                "Visits": "9982"
            },
            {
                "Date": "14",
                "Visits": "6850"
            },
            {
                "Date": "15",
                "Visits": "6861"
            },
            {
                "Date": "16",
                "Visits": "4717"
            },
            {
                "Date": "17",
                "Visits": "9837"
            },
            {
                "Date": "18",
                "Visits": "5738"
            },
            {
                "Date": "19",
                "Visits": "1310"
            },
            {
                "Date": "20",
                "Visits": "3191"
            }
        ]
    },
    {
        "Id": "2",
        "Title": "Ukraine forbereder tilbagetr\u00e6kning fra Bakhmut med nye skyttegrave",
        "Data": [
            {
                "Date": "06",
                "Visits": "0"
            },
            {
                "Date": "07",
                "Visits": "0"
            },
            {
                "Date": "08",
                "Visits": "0"
            },
            {
                "Date": "09",
                "Visits": "0"
            },
            {
                "Date": "10",
                "Visits": "0"
            },
            {
                "Date": "11",
                "Visits": "0"
            },
            {
                "Date": "12",
                "Visits": "7893"
            },
            {
                "Date": "13",
                "Visits": "1016"
            },
            {
                "Date": "14",
                "Visits": "9695"
            },
            {
                "Date": "15",
                "Visits": "4075"
            },
            {
                "Date": "16",
                "Visits": "5574"
            },
            {
                "Date": "17",
                "Visits": "8767"
            },
            {
                "Date": "18",
                "Visits": "2477"
            },
            {
                "Date": "19",
                "Visits": "4808"
            },
            {
                "Date": "20",
                "Visits": "4644"
            }
        ]
    },
    {
        "Id": "3",
        "Title": "Ruslands \"br\u00e6ndende sol\" skal redde vingeskudt luftstyrkes \u00e6re",
        "Data": [
            {
                "Date": "06",
                "Visits": "0"
            },
            {
                "Date": "07",
                "Visits": "0"
            },
            {
                "Date": "08",
                "Visits": "0"
            },
            {
                "Date": "09",
                "Visits": "0"
            },
            {
                "Date": "10",
                "Visits": "0"
            },
            {
                "Date": "11",
                "Visits": "0"
            },
            {
                "Date": "12",
                "Visits": "8071"
            },
            {
                "Date": "13",
                "Visits": "4958"
            },
            {
                "Date": "14",
                "Visits": "6706"
            },
            {
                "Date": "15",
                "Visits": "6958"
            },
            {
                "Date": "16",
                "Visits": "5767"
            },
            {
                "Date": "17",
                "Visits": "3999"
            },
            {
                "Date": "18",
                "Visits": "2420"
            },
            {
                "Date": "19",
                "Visits": "9375"
            },
            {
                "Date": "20",
                "Visits": "4276"
            }
        ]
    },
    {
        "Id": "4",
        "Title": "Medier: L\u00e6k afsl\u00f8rer Nato-styrkers tilstedev\u00e6relse i Ukraine",
        "Data": [
            {
                "Date": "06",
                "Visits": "0"
            },
            {
                "Date": "07",
                "Visits": "0"
            },
            {
                "Date": "08",
                "Visits": "0"
            },
            {
                "Date": "09",
                "Visits": "0"
            },
            {
                "Date": "10",
                "Visits": "0"
            },
            {
                "Date": "11",
                "Visits": "0"
            },
            {
                "Date": "12",
                "Visits": "1642"
            },
            {
                "Date": "13",
                "Visits": "7542"
            },
            {
                "Date": "14",
                "Visits": "3472"
            },
            {
                "Date": "15",
                "Visits": "1384"
            },
            {
                "Date": "16",
                "Visits": "3311"
            },
            {
                "Date": "17",
                "Visits": "4063"
            },
            {
                "Date": "18",
                "Visits": "7739"
            },
            {
                "Date": "19",
                "Visits": "3292"
            },
            {
                "Date": "20",
                "Visits": "5230"
            }
        ]
    },
    {
        "Id": "5",
        "Title": "Seneste nyt om krigen i Ukraine 12. april",
        "Data": [
            {
                "Date": "06",
                "Visits": "0"
            },
            {
                "Date": "07",
                "Visits": "0"
            },
            {
                "Date": "08",
                "Visits": "0"
            },
            {
                "Date": "09",
                "Visits": "0"
            },
            {
                "Date": "10",
                "Visits": "0"
            },
            {
                "Date": "11",
                "Visits": "0"
            },
            {
                "Date": "12",
                "Visits": "5402"
            },
            {
                "Date": "13",
                "Visits": "4922"
            },
            {
                "Date": "14",
                "Visits": "1920"
            },
            {
                "Date": "15",
                "Visits": "1104"
            },
            {
                "Date": "16",
                "Visits": "7381"
            },
            {
                "Date": "17",
                "Visits": "4340"
            },
            {
                "Date": "18",
                "Visits": "8469"
            },
            {
                "Date": "19",
                "Visits": "4056"
            },
            {
                "Date": "20",
                "Visits": "4056"
            }
        ]
    },
    {
        "Id": "6",
        "Title": "Russisk oppositionsleder er alvorligt syg, siger advokat",
        "Data": [
            {
                "Date": "06",
                "Visits": "0"
            },
            {
                "Date": "07",
                "Visits": "0"
            },
            {
                "Date": "08",
                "Visits": "0"
            },
            {
                "Date": "09",
                "Visits": "0"
            },
            {
                "Date": "10",
                "Visits": "0"
            },
            {
                "Date": "11",
                "Visits": "1992"
            },
            {
                "Date": "12",
                "Visits": "7498"
            },
            {
                "Date": "13",
                "Visits": "4336"
            },
            {
                "Date": "14",
                "Visits": "9596"
            },
            {
                "Date": "15",
                "Visits": "8516"
            },
            {
                "Date": "16",
                "Visits": "8317"
            },
            {
                "Date": "17",
                "Visits": "7322"
            },
            {
                "Date": "18",
                "Visits": "1435"
            },
            {
                "Date": "19",
                "Visits": "8133"
            },
            {
                "Date": "20",
                "Visits": "8330"
            }
        ]
    },
    {
        "Id": "7",
        "Title": "Russiske regioner frygter angreb \u2013 aflyser parader \"for ikke at provokere fjenden\"",
        "Data": [
            {
                "Date": "06",
                "Visits": "0"
            },
            {
                "Date": "07",
                "Visits": "0"
            },
            {
                "Date": "08",
                "Visits": "0"
            },
            {
                "Date": "09",
                "Visits": "0"
            },
            {
                "Date": "10",
                "Visits": "0"
            },
            {
                "Date": "11",
                "Visits": "9887"
            },
            {
                "Date": "12",
                "Visits": "2823"
            },
            {
                "Date": "13",
                "Visits": "5977"
            },
            {
                "Date": "14",
                "Visits": "5080"
            },
            {
                "Date": "15",
                "Visits": "2318"
            },
            {
                "Date": "16",
                "Visits": "2454"
            },
            {
                "Date": "17",
                "Visits": "1395"
            },
            {
                "Date": "18",
                "Visits": "3127"
            },
            {
                "Date": "19",
                "Visits": "8552"
            },
            {
                "Date": "20",
                "Visits": "9333"
            }
        ]
    },
    {
        "Id": "8",
        "Title": "Hun blev sendt til Danmark under krigen \u2013 nu gr\u00e6der hun for ukrainske b\u00f8rn",
        "Data": [
            {
                "Date": "06",
                "Visits": "0"
            },
            {
                "Date": "07",
                "Visits": "0"
            },
            {
                "Date": "08",
                "Visits": "0"
            },
            {
                "Date": "09",
                "Visits": "0"
            },
            {
                "Date": "10",
                "Visits": "0"
            },
            {
                "Date": "11",
                "Visits": "6067"
            },
            {
                "Date": "12",
                "Visits": "5565"
            },
            {
                "Date": "13",
                "Visits": "6679"
            },
            {
                "Date": "14",
                "Visits": "3167"
            },
            {
                "Date": "15",
                "Visits": "1111"
            },
            {
                "Date": "16",
                "Visits": "5949"
            },
            {
                "Date": "17",
                "Visits": "6320"
            },
            {
                "Date": "18",
                "Visits": "6590"
            },
            {
                "Date": "19",
                "Visits": "4631"
            },
            {
                "Date": "20",
                "Visits": "4630"
            }
        ]
    },
    {
        "Id": "9",
        "Title": "Russisk sammenst\u00f8d med britisk fly var mere alvorligt end beskrevet",
        "Data": [
            {
                "Date": "06",
                "Visits": "0"
            },
            {
                "Date": "07",
                "Visits": "0"
            },
            {
                "Date": "08",
                "Visits": "0"
            },
            {
                "Date": "09",
                "Visits": "0"
            },
            {
                "Date": "10",
                "Visits": "0"
            },
            {
                "Date": "11",
                "Visits": "6723"
            },
            {
                "Date": "12",
                "Visits": "4230"
            },
            {
                "Date": "13",
                "Visits": "3524"
            },
            {
                "Date": "14",
                "Visits": "1005"
            },
            {
                "Date": "15",
                "Visits": "8118"
            },
            {
                "Date": "16",
                "Visits": "8201"
            },
            {
                "Date": "17",
                "Visits": "1762"
            },
            {
                "Date": "18",
                "Visits": "3009"
            },
            {
                "Date": "19",
                "Visits": "7214"
            },
            {
                "Date": "20",
                "Visits": "5899"
            }
        ]
    },
    {
        "Id": "10",
        "Title": "Seneste nyt om krigen i Ukraine 11. april 2023",
        "Data": [
            {
                "Date": "06",
                "Visits": "0"
            },
            {
                "Date": "07",
                "Visits": "0"
            },
            {
                "Date": "08",
                "Visits": "0"
            },
            {
                "Date": "09",
                "Visits": "0"
            },
            {
                "Date": "10",
                "Visits": "0"
            },
            {
                "Date": "11",
                "Visits": "6765"
            },
            {
                "Date": "12",
                "Visits": "5221"
            },
            {
                "Date": "13",
                "Visits": "1465"
            },
            {
                "Date": "14",
                "Visits": "2072"
            },
            {
                "Date": "15",
                "Visits": "8920"
            },
            {
                "Date": "16",
                "Visits": "4364"
            },
            {
                "Date": "17",
                "Visits": "6094"
            },
            {
                "Date": "18",
                "Visits": "2022"
            },
            {
                "Date": "19",
                "Visits": "6805"
            },
            {
                "Date": "20",
                "Visits": "4571"
            }
        ]
    },
    {
        "Id": "11",
        "Title": "Forsvarsminister p\u00e5 bes\u00f8g i Ukraine: S\u00e6rligt \u00e9n dansk donation har givet ukrainerne en fordel",
        "Data": [
            {
                "Date": "06",
                "Visits": "0"
            },
            {
                "Date": "07",
                "Visits": "0"
            },
            {
                "Date": "08",
                "Visits": "0"
            },
            {
                "Date": "09",
                "Visits": "0"
            },
            {
                "Date": "10",
                "Visits": "6744"
            },
            {
                "Date": "11",
                "Visits": "7428"
            },
            {
                "Date": "12",
                "Visits": "9171"
            },
            {
                "Date": "13",
                "Visits": "1740"
            },
            {
                "Date": "14",
                "Visits": "7007"
            },
            {
                "Date": "15",
                "Visits": "1768"
            },
            {
                "Date": "16",
                "Visits": "1246"
            },
            {
                "Date": "17",
                "Visits": "9504"
            },
            {
                "Date": "18",
                "Visits": "2003"
            },
            {
                "Date": "19",
                "Visits": "1482"
            },
            {
                "Date": "20",
                "Visits": "7574"
            }
        ]
    },
    {
        "Id": "12",
        "Title": "Rusland vil opruste luftv\u00e6rn langs gr\u00e6nsen til Finland",
        "Data": [
            {
                "Date": "06",
                "Visits": "0"
            },
            {
                "Date": "07",
                "Visits": "0"
            },
            {
                "Date": "08",
                "Visits": "0"
            },
            {
                "Date": "09",
                "Visits": "0"
            },
            {
                "Date": "10",
                "Visits": "1820"
            },
            {
                "Date": "11",
                "Visits": "4689"
            },
            {
                "Date": "12",
                "Visits": "2045"
            },
            {
                "Date": "13",
                "Visits": "4099"
            },
            {
                "Date": "14",
                "Visits": "8953"
            },
            {
                "Date": "15",
                "Visits": "9502"
            },
            {
                "Date": "16",
                "Visits": "8913"
            },
            {
                "Date": "17",
                "Visits": "4944"
            },
            {
                "Date": "18",
                "Visits": "2658"
            },
            {
                "Date": "19",
                "Visits": "6532"
            },
            {
                "Date": "20",
                "Visits": "6842"
            }
        ]
    },
    {
        "Id": "13",
        "Title": "Seneste nyt om krigen i Ukraine 10. april",
        "Data": [
            {
                "Date": "06",
                "Visits": "0"
            },
            {
                "Date": "07",
                "Visits": "0"
            },
            {
                "Date": "08",
                "Visits": "0"
            },
            {
                "Date": "09",
                "Visits": "0"
            },
            {
                "Date": "10",
                "Visits": "4914"
            },
            {
                "Date": "11",
                "Visits": "9750"
            },
            {
                "Date": "12",
                "Visits": "3435"
            },
            {
                "Date": "13",
                "Visits": "1443"
            },
            {
                "Date": "14",
                "Visits": "9505"
            },
            {
                "Date": "15",
                "Visits": "4772"
            },
            {
                "Date": "16",
                "Visits": "2888"
            },
            {
                "Date": "17",
                "Visits": "2962"
            },
            {
                "Date": "18",
                "Visits": "5896"
            },
            {
                "Date": "19",
                "Visits": "8462"
            },
            {
                "Date": "20",
                "Visits": "2527"
            }
        ]
    },
    {
        "Id": "14",
        "Title": "Russisk offensiv n\u00e6rmer sig et vendepunkt, vurderer t\u00e6nketank",
        "Data": [
            {
                "Date": "06",
                "Visits": "0"
            },
            {
                "Date": "07",
                "Visits": "0"
            },
            {
                "Date": "08",
                "Visits": "0"
            },
            {
                "Date": "09",
                "Visits": "4159"
            },
            {
                "Date": "10",
                "Visits": "5187"
            },
            {
                "Date": "11",
                "Visits": "2795"
            },
            {
                "Date": "12",
                "Visits": "7934"
            },
            {
                "Date": "13",
                "Visits": "1884"
            },
            {
                "Date": "14",
                "Visits": "2891"
            },
            {
                "Date": "15",
                "Visits": "5935"
            },
            {
                "Date": "16",
                "Visits": "2433"
            },
            {
                "Date": "17",
                "Visits": "6392"
            },
            {
                "Date": "18",
                "Visits": "4581"
            },
            {
                "Date": "19",
                "Visits": "6053"
            },
            {
                "Date": "20",
                "Visits": "7166"
            }
        ]
    },
    {
        "Id": "15",
        "Title": "Paven appellerede til russerne i sit p\u00e5skebudskab",
        "Data": [
            {
                "Date": "06",
                "Visits": "0"
            },
            {
                "Date": "07",
                "Visits": "0"
            },
            {
                "Date": "08",
                "Visits": "0"
            },
            {
                "Date": "09",
                "Visits": "7694"
            },
            {
                "Date": "10",
                "Visits": "3360"
            },
            {
                "Date": "11",
                "Visits": "6091"
            },
            {
                "Date": "12",
                "Visits": "8150"
            },
            {
                "Date": "13",
                "Visits": "6275"
            },
            {
                "Date": "14",
                "Visits": "1783"
            },
            {
                "Date": "15",
                "Visits": "3766"
            },
            {
                "Date": "16",
                "Visits": "9827"
            },
            {
                "Date": "17",
                "Visits": "7340"
            },
            {
                "Date": "18",
                "Visits": "5725"
            },
            {
                "Date": "19",
                "Visits": "5749"
            },
            {
                "Date": "20",
                "Visits": "5861"
            }
        ]
    },
    {
        "Id": "16",
        "Title": "13-\u00e5rig ukrainsk dreng sat fri efter halvt \u00e5r i russisk lejr \u2013 TV 2 overv\u00e6rede hans genforening med mor",
        "Data": [
            {
                "Date": "06",
                "Visits": "0"
            },
            {
                "Date": "07",
                "Visits": "0"
            },
            {
                "Date": "08",
                "Visits": "0"
            },
            {
                "Date": "09",
                "Visits": "7307"
            },
            {
                "Date": "10",
                "Visits": "2648"
            },
            {
                "Date": "11",
                "Visits": "8760"
            },
            {
                "Date": "12",
                "Visits": "1851"
            },
            {
                "Date": "13",
                "Visits": "9675"
            },
            {
                "Date": "14",
                "Visits": "1722"
            },
            {
                "Date": "15",
                "Visits": "2516"
            },
            {
                "Date": "16",
                "Visits": "3926"
            },
            {
                "Date": "17",
                "Visits": "3543"
            },
            {
                "Date": "18",
                "Visits": "6209"
            },
            {
                "Date": "19",
                "Visits": "9851"
            },
            {
                "Date": "20",
                "Visits": "2132"
            }
        ]
    },
    {
        "Id": "17",
        "Title": "Aktivist afsl\u00f8rede soldaters massegrave \u2013 nu har han forladt Rusland",
        "Data": [
            {
                "Date": "06",
                "Visits": "0"
            },
            {
                "Date": "07",
                "Visits": "0"
            },
            {
                "Date": "08",
                "Visits": "0"
            },
            {
                "Date": "09",
                "Visits": "8991"
            },
            {
                "Date": "10",
                "Visits": "2632"
            },
            {
                "Date": "11",
                "Visits": "5033"
            },
            {
                "Date": "12",
                "Visits": "4943"
            },
            {
                "Date": "13",
                "Visits": "1238"
            },
            {
                "Date": "14",
                "Visits": "2251"
            },
            {
                "Date": "15",
                "Visits": "7333"
            },
            {
                "Date": "16",
                "Visits": "4173"
            },
            {
                "Date": "17",
                "Visits": "3050"
            },
            {
                "Date": "18",
                "Visits": "2519"
            },
            {
                "Date": "19",
                "Visits": "5099"
            },
            {
                "Date": "20",
                "Visits": "7079"
            }
        ]
    },
    {
        "Id": "18",
        "Title": "Seneste nyt om krigen i Ukraine 9. april",
        "Data": [
            {
                "Date": "06",
                "Visits": "0"
            },
            {
                "Date": "07",
                "Visits": "0"
            },
            {
                "Date": "08",
                "Visits": "0"
            },
            {
                "Date": "09",
                "Visits": "1055"
            },
            {
                "Date": "10",
                "Visits": "7310"
            },
            {
                "Date": "11",
                "Visits": "2197"
            },
            {
                "Date": "12",
                "Visits": "1458"
            },
            {
                "Date": "13",
                "Visits": "8808"
            },
            {
                "Date": "14",
                "Visits": "9859"
            },
            {
                "Date": "15",
                "Visits": "8476"
            },
            {
                "Date": "16",
                "Visits": "9108"
            },
            {
                "Date": "17",
                "Visits": "2172"
            },
            {
                "Date": "18",
                "Visits": "1588"
            },
            {
                "Date": "19",
                "Visits": "1021"
            },
            {
                "Date": "20",
                "Visits": "9087"
            }
        ]
    },
    {
        "Id": "19",
        "Title": "Rusland forbereder tvangsevakuering, viser efterretninger",
        "Data": [
            {
                "Date": "06",
                "Visits": "0"
            },
            {
                "Date": "07",
                "Visits": "0"
            },
            {
                "Date": "08",
                "Visits": "3311"
            },
            {
                "Date": "09",
                "Visits": "2182"
            },
            {
                "Date": "10",
                "Visits": "7395"
            },
            {
                "Date": "11",
                "Visits": "4855"
            },
            {
                "Date": "12",
                "Visits": "1910"
            },
            {
                "Date": "13",
                "Visits": "9551"
            },
            {
                "Date": "14",
                "Visits": "1667"
            },
            {
                "Date": "15",
                "Visits": "5505"
            },
            {
                "Date": "16",
                "Visits": "7501"
            },
            {
                "Date": "17",
                "Visits": "2621"
            },
            {
                "Date": "18",
                "Visits": "5059"
            },
            {
                "Date": "19",
                "Visits": "8979"
            },
            {
                "Date": "20",
                "Visits": "2694"
            }
        ]
    },
    {
        "Id": "20",
        "Title": "Pentagon efterforsker 'l\u00e6kkede' dokumenter om tabstal \u2013 dansk ekspert kalder tallene fabrikerede",
        "Data": [
            {
                "Date": "06",
                "Visits": "0"
            },
            {
                "Date": "07",
                "Visits": "2193"
            },
            {
                "Date": "08",
                "Visits": "8218"
            },
            {
                "Date": "09",
                "Visits": "8389"
            },
            {
                "Date": "10",
                "Visits": "1875"
            },
            {
                "Date": "11",
                "Visits": "2470"
            },
            {
                "Date": "12",
                "Visits": "6669"
            },
            {
                "Date": "13",
                "Visits": "5287"
            },
            {
                "Date": "14",
                "Visits": "4482"
            },
            {
                "Date": "15",
                "Visits": "3248"
            },
            {
                "Date": "16",
                "Visits": "8795"
            },
            {
                "Date": "17",
                "Visits": "6008"
            },
            {
                "Date": "18",
                "Visits": "4253"
            },
            {
                "Date": "19",
                "Visits": "5160"
            },
            {
                "Date": "20",
                "Visits": "1762"
            }
        ]
    },
    {
        "Id": "21",
        "Title": "Ukrainske b\u00f8rn deporteres til Rusland: - Alle var venlige mod os",
        "Data": [
            {
                "Date": "06",
                "Visits": "0"
            },
            {
                "Date": "07",
                "Visits": "8032"
            },
            {
                "Date": "08",
                "Visits": "7979"
            },
            {
                "Date": "09",
                "Visits": "9829"
            },
            {
                "Date": "10",
                "Visits": "5179"
            },
            {
                "Date": "11",
                "Visits": "7619"
            },
            {
                "Date": "12",
                "Visits": "3102"
            },
            {
                "Date": "13",
                "Visits": "1255"
            },
            {
                "Date": "14",
                "Visits": "9907"
            },
            {
                "Date": "15",
                "Visits": "5866"
            },
            {
                "Date": "16",
                "Visits": "2253"
            },
            {
                "Date": "17",
                "Visits": "6261"
            },
            {
                "Date": "18",
                "Visits": "5387"
            },
            {
                "Date": "19",
                "Visits": "1721"
            },
            {
                "Date": "20",
                "Visits": "9150"
            }
        ]
    },
    {
        "Id": "22",
        "Title": "Rusland advarer kineserne: - Kina er Vestens n\u00e6ste m\u00e5l",
        "Data": [
            {
                "Date": "06",
                "Visits": "0"
            },
            {
                "Date": "07",
                "Visits": "1376"
            },
            {
                "Date": "08",
                "Visits": "3016"
            },
            {
                "Date": "09",
                "Visits": "1413"
            },
            {
                "Date": "10",
                "Visits": "2595"
            },
            {
                "Date": "11",
                "Visits": "1111"
            },
            {
                "Date": "12",
                "Visits": "9623"
            },
            {
                "Date": "13",
                "Visits": "9240"
            },
            {
                "Date": "14",
                "Visits": "4259"
            },
            {
                "Date": "15",
                "Visits": "4150"
            },
            {
                "Date": "16",
                "Visits": "5842"
            },
            {
                "Date": "17",
                "Visits": "1629"
            },
            {
                "Date": "18",
                "Visits": "8715"
            },
            {
                "Date": "19",
                "Visits": "1664"
            },
            {
                "Date": "20",
                "Visits": "4247"
            }
        ]
    },
    {
        "Id": "23",
        "Title": "Rusland har genvundet momentum i Bakhmut, viser nye efterretninger",
        "Data": [
            {
                "Date": "06",
                "Visits": "0"
            },
            {
                "Date": "07",
                "Visits": "6931"
            },
            {
                "Date": "08",
                "Visits": "9793"
            },
            {
                "Date": "09",
                "Visits": "3582"
            },
            {
                "Date": "10",
                "Visits": "3413"
            },
            {
                "Date": "11",
                "Visits": "5416"
            },
            {
                "Date": "12",
                "Visits": "7629"
            },
            {
                "Date": "13",
                "Visits": "4353"
            },
            {
                "Date": "14",
                "Visits": "7704"
            },
            {
                "Date": "15",
                "Visits": "2612"
            },
            {
                "Date": "16",
                "Visits": "3921"
            },
            {
                "Date": "17",
                "Visits": "7487"
            },
            {
                "Date": "18",
                "Visits": "6473"
            },
            {
                "Date": "19",
                "Visits": "1151"
            },
            {
                "Date": "20",
                "Visits": "3832"
            }
        ]
    },
    {
        "Id": "24",
        "Title": "Virksomheder har hentet hundredvis af russere til Danmark efter invasion",
        "Data": [
            {
                "Date": "06",
                "Visits": "0"
            },
            {
                "Date": "07",
                "Visits": "9893"
            },
            {
                "Date": "08",
                "Visits": "7528"
            },
            {
                "Date": "09",
                "Visits": "6001"
            },
            {
                "Date": "10",
                "Visits": "4621"
            },
            {
                "Date": "11",
                "Visits": "4831"
            },
            {
                "Date": "12",
                "Visits": "7173"
            },
            {
                "Date": "13",
                "Visits": "7113"
            },
            {
                "Date": "14",
                "Visits": "7612"
            },
            {
                "Date": "15",
                "Visits": "2129"
            },
            {
                "Date": "16",
                "Visits": "7873"
            },
            {
                "Date": "17",
                "Visits": "1246"
            },
            {
                "Date": "18",
                "Visits": "7317"
            },
            {
                "Date": "19",
                "Visits": "2145"
            },
            {
                "Date": "20",
                "Visits": "9597"
            }
        ]
    },
    {
        "Id": "25",
        "Title": "Krigen i Ukraine 7. april",
        "Data": [
            {
                "Date": "06",
                "Visits": "0"
            },
            {
                "Date": "07",
                "Visits": "9948"
            },
            {
                "Date": "08",
                "Visits": "4577"
            },
            {
                "Date": "09",
                "Visits": "2853"
            },
            {
                "Date": "10",
                "Visits": "4211"
            },
            {
                "Date": "11",
                "Visits": "2464"
            },
            {
                "Date": "12",
                "Visits": "8404"
            },
            {
                "Date": "13",
                "Visits": "8362"
            },
            {
                "Date": "14",
                "Visits": "6857"
            },
            {
                "Date": "15",
                "Visits": "9661"
            },
            {
                "Date": "16",
                "Visits": "3784"
            },
            {
                "Date": "17",
                "Visits": "2072"
            },
            {
                "Date": "18",
                "Visits": "1104"
            },
            {
                "Date": "19",
                "Visits": "5844"
            },
            {
                "Date": "20",
                "Visits": "6112"
            }
        ]
    },
    {
        "Id": "26",
        "Title": "Rusland kan mobilisere 400.000 til \u00e9t sidste angreb, advarer Putin-r\u00e5dgiver",
        "Data": [
            {
                "Date": "06",
                "Visits": "2722"
            },
            {
                "Date": "07",
                "Visits": "3837"
            },
            {
                "Date": "08",
                "Visits": "3792"
            },
            {
                "Date": "09",
                "Visits": "3027"
            },
            {
                "Date": "10",
                "Visits": "6518"
            },
            {
                "Date": "11",
                "Visits": "2223"
            },
            {
                "Date": "12",
                "Visits": "5140"
            },
            {
                "Date": "13",
                "Visits": "7440"
            },
            {
                "Date": "14",
                "Visits": "3628"
            },
            {
                "Date": "15",
                "Visits": "6841"
            },
            {
                "Date": "16",
                "Visits": "6748"
            },
            {
                "Date": "17",
                "Visits": "9159"
            },
            {
                "Date": "18",
                "Visits": "1374"
            },
            {
                "Date": "19",
                "Visits": "3014"
            },
            {
                "Date": "20",
                "Visits": "5621"
            }
        ]
    },
    {
        "Id": "27",
        "Title": "Milit\u00e6ranalytiker kalder opsigtsv\u00e6kkende Krim-melding for \"et signal til Vesten\"",
        "Data": [
            {
                "Date": "06",
                "Visits": "9136"
            },
            {
                "Date": "07",
                "Visits": "7557"
            },
            {
                "Date": "08",
                "Visits": "2685"
            },
            {
                "Date": "09",
                "Visits": "4440"
            },
            {
                "Date": "10",
                "Visits": "1531"
            },
            {
                "Date": "11",
                "Visits": "9482"
            },
            {
                "Date": "12",
                "Visits": "9675"
            },
            {
                "Date": "13",
                "Visits": "9788"
            },
            {
                "Date": "14",
                "Visits": "3938"
            },
            {
                "Date": "15",
                "Visits": "1436"
            },
            {
                "Date": "16",
                "Visits": "6042"
            },
            {
                "Date": "17",
                "Visits": "7721"
            },
            {
                "Date": "18",
                "Visits": "7907"
            },
            {
                "Date": "19",
                "Visits": "2532"
            },
            {
                "Date": "20",
                "Visits": "2351"
            }
        ]
    }
]